Metadata-Version: 2.1
Name: example_package_alexis
Version: 0.0.2
Summary: Esta es la descripción del paquete
Author: Alexis Barria
Author-email: alexis.barria.c@outlook.cl
License: MIT
License-File: LICENSE
